Metadata-Version: 2.1
Name: simple-django-api
Version: 1.1.0
Summary: simple rest api support for django
Home-page: UNKNOWN
Author: Abraham
Author-email: abraham.liu@hotmail.com
License: BSD
Platform: UNKNOWN
Classifier: Development Status :: 5 - Production/Stable
Classifier: Intended Audience :: Developers
Classifier: Intended Audience :: System Administrators
Classifier: Operating System :: OS Independent
Classifier: Programming Language :: Python
Classifier: Topic :: Utilities
Requires-Python: >=3.6
Requires-Dist: Django
Provides-Extra: jwt
Requires-Dist: PyJWT ; extra == 'jwt'
